.clang-format
.gitignore
MANIFEST.in
README.md
format.sh
generate_image.py
get_gsl.sh
jn_speed.py
license.txt
make_setup.py
makefile
pyproject.toml
setup.py
tst_cil.py
tst_pixel_bounce.py
include/ccd.hpp
include/cti.hpp
include/roe.hpp
include/trap_managers.hpp
include/traps.hpp
include/util.hpp
python/arcticpy/__init__.py
python/arcticpy/ccd.py
python/arcticpy/cti.py
python/arcticpy/pixel_bounce.py
python/arcticpy/read_noise.py
python/arcticpy/roe.py
python/arcticpy/traps.py
python/arcticpy/wrapper.cpp
python/arcticpy/wrapper.pyx
python/arcticpy/include/interface.hpp
python/arcticpy/src/interface.cpp
python/arcticpytest.egg-info/PKG-INFO
python/arcticpytest.egg-info/SOURCES.txt
python/arcticpytest.egg-info/dependency_links.txt
python/arcticpytest.egg-info/not-zip-safe
python/arcticpytest.egg-info/requires.txt
python/arcticpytest.egg-info/top_level.txt
src/ccd.cpp
src/cti.cpp
src/main.cpp
src/roe.cpp
src/trap_managers.cpp
src/traps.cpp
src/util.cpp
test/test_arcticpy.py
test/test_ccd.cpp
test/test_cti.cpp
test/test_lib.cpp
test/test_main.cpp
test/test_roe.cpp
test/test_trap_managers.cpp
test/test_traps.cpp
test/test_util.cpp
test/catch2/catch.hpp
test/files/.gitignore