Metadata-Version: 2.1
Name: arcticpytest
Version: 1.0
Summary: This is the python module for the arCTIc code
Author-email: Richard Massey <r.j.massey@durham.ac.uk>
Requires-Python: >=3.6
Provides-Extra: pytest
